dbbs_mod_collection/__init__.py
dbbs_mod_collection/mod/glia__dbbs_mod_collection__AMPA__0.mod
dbbs_mod_collection/mod/glia__dbbs_mod_collection__AMPA__granule.mod
dbbs_mod_collection/mod/glia__dbbs_mod_collection__CaL13__0.mod
dbbs_mod_collection/mod/glia__dbbs_mod_collection__Ca__granule_cell.mod
dbbs_mod_collection/mod/glia__dbbs_mod_collection__Cav2_1__0.mod
dbbs_mod_collection/mod/glia__dbbs_mod_collection__Cav2_2__0.mod
dbbs_mod_collection/mod/glia__dbbs_mod_collection__Cav2_3__0.mod
dbbs_mod_collection/mod/glia__dbbs_mod_collection__Cav3_1__0.mod
dbbs_mod_collection/mod/glia__dbbs_mod_collection__Cav3_2__0.mod
dbbs_mod_collection/mod/glia__dbbs_mod_collection__Cav3_3__0.mod
dbbs_mod_collection/mod/glia__dbbs_mod_collection__GABA__0.mod
dbbs_mod_collection/mod/glia__dbbs_mod_collection__GABA__biexp.mod
dbbs_mod_collection/mod/glia__dbbs_mod_collection__GABA__granule.mod
dbbs_mod_collection/mod/glia__dbbs_mod_collection__HCN1__0.mod
dbbs_mod_collection/mod/glia__dbbs_mod_collection__HCN1__golgi.mod
dbbs_mod_collection/mod/glia__dbbs_mod_collection__HCN2__0.mod
dbbs_mod_collection/mod/glia__dbbs_mod_collection__Kca1_1__0.mod
dbbs_mod_collection/mod/glia__dbbs_mod_collection__Kca2_2__0.mod
dbbs_mod_collection/mod/glia__dbbs_mod_collection__Kca3_1__0.mod
dbbs_mod_collection/mod/glia__dbbs_mod_collection__Kir2_3__0.mod
dbbs_mod_collection/mod/glia__dbbs_mod_collection__Km__granule_cell.mod
dbbs_mod_collection/mod/glia__dbbs_mod_collection__Kv1_1__0.mod
dbbs_mod_collection/mod/glia__dbbs_mod_collection__Kv1_5__0.mod
dbbs_mod_collection/mod/glia__dbbs_mod_collection__Kv2_2__0.mod
dbbs_mod_collection/mod/glia__dbbs_mod_collection__Kv3_3__0.mod
dbbs_mod_collection/mod/glia__dbbs_mod_collection__Kv3_4__0.mod
dbbs_mod_collection/mod/glia__dbbs_mod_collection__Kv4_3__0.mod
dbbs_mod_collection/mod/glia__dbbs_mod_collection__Kv7__0.mod
dbbs_mod_collection/mod/glia__dbbs_mod_collection__Leak__0.mod
dbbs_mod_collection/mod/glia__dbbs_mod_collection__Leak__GABA.mod
dbbs_mod_collection-2.2.3.dist-info/METADATA
dbbs_mod_collection-2.2.3.dist-info/WHEEL
dbbs_mod_collection-2.2.3.dist-info/entry_points.txt
dbbs_mod_collection-2.2.3.dist-info/top_level.txt
dbbs_mod_collection-2.2.3.dist-info/RECORD
